README.md
setup.py
rem_calc/__init__.py
rem_calc/rem.py
rem_calc/rem_calc.py
rem_calc.egg-info/PKG-INFO
rem_calc.egg-info/SOURCES.txt
rem_calc.egg-info/dependency_links.txt
rem_calc.egg-info/entry_points.txt
rem_calc.egg-info/requires.txt
rem_calc.egg-info/top_level.txt