Metadata-Version: 2.1
Name: rem-calc
Version: 1.1.0
Summary: rem-calc helps you to calculate rem values based on pixel values.
Home-page: https://github.com/KurzGedanke/rem-calc
Author: KurzGedanke
Author-email: rem_calc@kurzgedanke.me
License: MIT
Download-URL: https://github.com/KurzGedanke/rem-calc/archive/v1.1.0.tar.gz
Keywords: rem css webdev
Platform: UNKNOWN
Classifier: Development Status :: 5 - Production/Stable
Classifier: Intended Audience :: Developers
Classifier: Topic :: Software Development :: Build Tools
Classifier: License :: OSI Approved :: MIT License
Classifier: Programming Language :: Python :: 3.6
Classifier: Programming Language :: Python :: 3.7
Classifier: Programming Language :: Python :: 3.8
